{
  "concept_id": "fill_rect_interiors_by_size",
  "version": 1,
  "description": "Find rectangles bordered by a single color with empty interiors. Fill interiors by area rank: largest gets 8, next gets 7, next gets 6, etc.",
  "signature": {
    "grid_size_preserved": true,
    "color_preserved": false,
    "requires_content_diff": true
  },
  "parameters": {
    "border_color": {"type": "color", "infer": "from_examples"},
    "bg": {"type": "color", "default": 0}
  },
  "steps": [
    {"id": "s1", "primitive": "fill_rect_interiors_by_size", "args": {"grid": "$input", "border_color": "$border_color", "bg": "$bg"}, "output": "result"}
  ],
  "result": "$result"
}
