{
  "rule_id": "chunked_20260406_054944_vertical_mirror_recolor",
  "source": "chunked",
  "source_tasks": [
    "ce039d91"
  ],
  "times_validated": 1,
  "times_failed": 0,
  "condition": {
    "level": "GRID",
    "topology": {
      "color": "DIFF",
      "contents": {
        "type": "DIFF",
        "change_pattern": "multi_group",
        "change_scope": "subset",
        "num_groups_consistent": false,
        "group_anchors_consistent": false
      },
      "size": "COMM"
    }
  },
  "action": {
    "concept": "vertical_mirror_recolor",
    "param_source": "inferred(bg), inferred(fg_color), inferred(new_color)"
  }
}